wop_flasktray/__init__.py
wop_flasktray-1.0.0.dist-info/LICENSE
wop_flasktray-1.0.0.dist-info/METADATA
wop_flasktray-1.0.0.dist-info/WHEEL
wop_flasktray-1.0.0.dist-info/top_level.txt
wop_flasktray-1.0.0.dist-info/RECORD
