Metadata-Version: 2.1
Name: wop-flasktray
Version: 1.0.0
Summary: Starts a Flaskapp with a trayicon using waitress and pystray.
Author: wopwopwopwopwop
License: Copyright (c) 2023 wopwopwopwopwop
Project-URL: Homepage, https://github.com/wopwopwopwopwop/wop_flasktray
Classifier: Programming Language :: Python :: 3
Classifier: License :: OSI Approved :: MIT License
Classifier: Operating System :: OS Independent
Requires-Python: >=3.7.0
License-File: LICENSE
